stygtfo/__init__.py
stygtfo/__main__.py
stygtfo-0.1.0.dist-info/entry_points.txt
stygtfo-0.1.0.dist-info/WHEEL
stygtfo-0.1.0.dist-info/METADATA
stygtfo-0.1.0.dist-info/RECORD
