Metadata-Version: 2.1
Name: stygtfo
Version: 0.1.0
Summary: A simple tool to comment out packages not used in a latex document
Author: notPlancha
Author-email: andre.plancha@hotmail.com
Requires-Python: >=3.11,<4.0
Classifier: Programming Language :: Python :: 3
Classifier: Programming Language :: Python :: 3.11
Requires-Dist: diff-pdf-visually (>=1.7.0,<2.0.0)
